dlshogi/__init__.py
dlshogi/common.py
dlshogi/convert_model_to_onnx.py
dlshogi/cppshogi.cp38-win_amd64.pyd
dlshogi/data_loader.py
dlshogi/serializers.py
dlshogi/test.py
dlshogi/train.py
dlshogi/network/policy_value_network.py
dlshogi/network/policy_value_network_resnet.py
dlshogi/network/policy_value_network_resnet10_swish.py
dlshogi/network/policy_value_network_senet.py
dlshogi/network/policy_value_network_wideresnet10.py
dlshogi/utils/__init__.py
dlshogi/utils/aoba_to_hcpe.py
dlshogi/utils/aoba_to_hcpe2.py
dlshogi/utils/aoba_to_hcpe3.py
dlshogi/utils/append_book.py
dlshogi/utils/benchmark.py
dlshogi/utils/build_onnx.py
dlshogi/utils/clean_hcpe3.py
dlshogi/utils/csa_to_book.py
dlshogi/utils/csa_to_gokakusfen.py
dlshogi/utils/csa_to_hcp.py
dlshogi/utils/csa_to_hcpe.py
dlshogi/utils/csa_to_hcpe2.py
dlshogi/utils/csa_to_hcpe3.py
dlshogi/utils/csa_to_roots_hcp.py
dlshogi/utils/delete_hcp.py
dlshogi/utils/delete_hcp_by_usi.py
dlshogi/utils/filter_csa_in_dir.py
dlshogi/utils/filter_kif_in_dir.py
dlshogi/utils/fix_hcpe_eval.py
dlshogi/utils/hcp_uniq.py
dlshogi/utils/hcpe3_to_csa.py
dlshogi/utils/hcpe3_to_hcpe.py
dlshogi/utils/hcpe_to_psv.py
dlshogi/utils/kif_to_pgn.py
dlshogi/utils/kifustat.py
dlshogi/utils/matches.py
dlshogi/utils/merge_book.py
dlshogi/utils/plot_log_policy_value.py
dlshogi/utils/print_hcpe.py
dlshogi/utils/psv_to_hcp.py
dlshogi/utils/psv_to_hcpe.py
dlshogi/utils/sample_hcpe.py
dlshogi/utils/sfen_to_hcp.py
dlshogi/utils/split_hcpe.py
dlshogi/utils/split_hcpe3.py
dlshogi/utils/split_pgn.py
dlshogi/utils/stat_csa_in_dir.py
dlshogi/utils/stat_csa_position_in_dir.py
dlshogi/utils/stat_hcpe3.py
dlshogi/utils/uniq_hcpe.py
dlshogi/utils/usi_params_optimizer.py
dlshogi/utils/yanebook_to_hcp.py
dlshogi-0.1.1.dist-info/LICENSE
dlshogi-0.1.1.dist-info/METADATA
dlshogi-0.1.1.dist-info/WHEEL
dlshogi-0.1.1.dist-info/top_level.txt
dlshogi-0.1.1.dist-info/RECORD
