Metadata-Version: 2.1
Name: dlshogi
Version: 0.1.1
Summary: DeepLearningShogi(dlshogi)
Home-page: https://github.com/TadaoYamaoka/DeepLearningShogi
Author: Tadao Yamaoka
Author-email: UNKNOWN
License: UNKNOWN
Platform: UNKNOWN
Classifier: Programming Language :: Python :: 3
Classifier: License :: OSI Approved :: GNU General Public License (GPL)
Classifier: Operating System :: OS Independent
